pyrcf/__init__.py
pyrcf/variables.py
pyrcf/components/__init__.py
pyrcf/components/pyrcf_component.py
pyrcf/components/agents/__init__.py
pyrcf/components/agents/agent_base.py
pyrcf/components/agents/ml_agent_base.py
pyrcf/components/agents/planner_controller_agent.py
pyrcf/components/agents/torchscript_agent_base.py
pyrcf/components/callback_handlers/__init__.py
pyrcf/components/callback_handlers/base_callbacks.py
pyrcf/components/callback_handlers/pb_gui_callbacks.py
pyrcf/components/callback_handlers/pb_gui_utils.py
pyrcf/components/controller_manager/__init__.py
pyrcf/components/controller_manager/controller_manager_base.py
pyrcf/components/controller_manager/simple_controller_manager.py
pyrcf/components/controller_manager/command_accumulators/__init__.py
pyrcf/components/controller_manager/command_accumulators/cmd_accumulation_policies.py
pyrcf/components/controllers/__init__.py
pyrcf/components/controllers/controller_base.py
pyrcf/components/controllers/gravity_compensated_joint_pd_controller.py
pyrcf/components/controllers/joint_pd_controller.py
pyrcf/components/controllers/segway_pid_balance_controller.py
pyrcf/components/ctrl_loop_debuggers/__init__.py
pyrcf/components/ctrl_loop_debuggers/ctrl_loop_data_publisher_base.py
pyrcf/components/ctrl_loop_debuggers/ctrl_loop_debugger_base.py
pyrcf/components/ctrl_loop_debuggers/data_publish_debuggers.py
pyrcf/components/ctrl_loop_debuggers/data_recorder_debugger.py
pyrcf/components/ctrl_loop_debuggers/pybullet_robot_plan_debugger.py
pyrcf/components/ctrl_loop_debuggers/pybullet_robot_state_debugger.py
pyrcf/components/global_planners/__init__.py
pyrcf/components/global_planners/global_planner_base.py
pyrcf/components/global_planners/ui_reference_generators/__init__.py
pyrcf/components/global_planners/ui_reference_generators/joystick_interface.py
pyrcf/components/global_planners/ui_reference_generators/key_mappings.py
pyrcf/components/global_planners/ui_reference_generators/keyboard_interface.py
pyrcf-0.0.6.dist-info/LICENSE
pyrcf-0.0.6.dist-info/METADATA
pyrcf-0.0.6.dist-info/WHEEL
pyrcf-0.0.6.dist-info/entry_points.txt
pyrcf-0.0.6.dist-info/top_level.txt
pyrcf-0.0.6.dist-info/RECORD
