Metadata-Version: 2.1
Name: pyrcf
Version: 0.0.6
Summary: A Python Robot Control Framework for quickly prototyping control algorithms for different robot embodiments.
Author-email: Saif Sidhik <mail@saifsidhik.page>
Project-URL: Source, https://github.com/justagist/pyrcf
Project-URL: Home, https://github.com/justagist/pyrcf
Requires-Python: >=3.10
License-File: LICENSE
Requires-Dist: pybullet <4,>=3.2.6
Requires-Dist: pin <3,>=2.7.0
Requires-Dist: pybullet-robot >=0.1.4
Requires-Dist: yourdfpy >=0.0.56
Requires-Dist: scipy <2,>=1.14.0
Requires-Dist: pygame <3,>=2.6.0
Requires-Dist: numpy >=1.26
Requires-Dist: inputs >=0.5
Requires-Dist: numpy-quaternion >=2023.0.4
Requires-Dist: zmq >=0.0.0
Provides-Extra: docs
Requires-Dist: sphinxcontrib-napoleon ; extra == 'docs'
Requires-Dist: sphinx-rtd-theme ; extra == 'docs'
Requires-Dist: sphinx-autoapi ; extra == 'docs'
Provides-Extra: test
Requires-Dist: black <=24.4.2,>=23 ; extra == 'test'
Requires-Dist: pylint <=3.2.6,>=2.17.7 ; extra == 'test'
Requires-Dist: pytest-cov <=5.0.0,>=4.1 ; extra == 'test'
Requires-Dist: pytest <=8.3.2,>=7.4 ; extra == 'test'
Requires-Dist: hypothesis <=6.108.5,>=6.82 ; extra == 'test'
Requires-Dist: ruff <=0.5.5,>=0.0.280 ; extra == 'test'
Requires-Dist: coverage <=7.6.0,>=7.2.7 ; extra == 'test'
